README.rst
setup.cfg
setup.py
async_promises/__init__.py
async_promises/async_promises.py
async_promises/compat.py
async_promises/iterate_promise.py
async_promises.egg-info/PKG-INFO
async_promises.egg-info/SOURCES.txt
async_promises.egg-info/dependency_links.txt
async_promises.egg-info/requires.txt
async_promises.egg-info/top_level.txt