Metadata-Version: 1.1
Name: async-promises
Version: 1.1.0
Summary: (Fork of) Promises/A+ implementation for Python
Home-page: https://github.com/p2p-today/promise
Author: Syrus Akbary
Author-email: me@syrusakbary.com
License: MIT
Keywords: concurrent future deferred promise
Platform: UNKNOWN
Classifier: Development Status :: 5 - Production/Stable
Classifier: Intended Audience :: Developers
Classifier: Topic :: Software Development :: Libraries
Classifier: Programming Language :: Python :: 2
Classifier: Programming Language :: Python :: 2.7
Classifier: Programming Language :: Python :: 3
Classifier: Programming Language :: Python :: 3.3
Classifier: Programming Language :: Python :: 3.4
Classifier: Programming Language :: Python :: 3.5
Classifier: Programming Language :: Python :: Implementation :: PyPy
Classifier: License :: OSI Approved :: MIT License
